kustomize/__init__.py
kustomize/__main__.py
kustomize/cli.py
kustomize/commands/__init__.py
kustomize/commands/apply.py
kustomize/commands/build.py
kustomize/commands/lint.py
kustomize/commands/version.py
kustomize/helpers/__init__.py
kustomize/helpers/archive.py
kustomize/helpers/binaries.py
kustomize/helpers/download.py
kustomize_wrapper-0.16.0.dist-info/LICENSE
kustomize_wrapper-0.16.0.dist-info/METADATA
kustomize_wrapper-0.16.0.dist-info/WHEEL
kustomize_wrapper-0.16.0.dist-info/entry_points.txt
kustomize_wrapper-0.16.0.dist-info/top_level.txt
kustomize_wrapper-0.16.0.dist-info/RECORD
