Metadata-Version: 2.1
Name: kustomize-wrapper
Version: 0.16.0
Summary: A wrapper for Kustomize and related tooling
Author-email: Peter Bittner <peter@painless.software>
Maintainer-email: Peter Bittner <peter@painless.software>
License: Apache License
Project-URL: homepage, https://github.com/painless-software/kustomize-wrapper
Keywords: kubernetes,kustomize
Classifier: Development Status :: 4 - Beta
Classifier: Intended Audience :: System Administrators
Classifier: License :: OSI Approved :: Apache Software License
Classifier: Programming Language :: Python :: 3
Classifier: Programming Language :: Python :: 3.7
Classifier: Programming Language :: Python :: 3.8
Classifier: Programming Language :: Python :: 3.9
Classifier: Programming Language :: Python :: 3.10
Classifier: Programming Language :: Python :: 3.11
Classifier: Programming Language :: Python :: Implementation :: CPython
Classifier: Programming Language :: Python :: Implementation :: PyPy
Classifier: Topic :: System :: Networking
Classifier: Topic :: Utilities
Requires-Python: >=3.7
License-File: LICENSE
Requires-Dist: click
Requires-Dist: requests
Requires-Dist: importlib-metadata ; python_version < "3.8"
